{
    "1": {
        "title": "Sign Up",
        "type": "object",
        "properties": {
            "socialLogins": {
                "type": "string"
            }
        }
    },
    "2": {
        "title": "Sign Up",
        "type": "object",
        "required": [
            "email",
            "password",
            "confirm"
        ],
        "properties": {
            "email": {
                "type": "string",
                "title": "Email",
                "format": "email"
            },
            "password": {
                "type": "string",
                "title": "Password",
                "minLength": 8
            },
            "confirm": {
                "type": "string",
                "title": "Confirm Password",
                "minLength": 8
            }
        }
    },
    "3": {
        "title": "Sign Up",
        "type": "object",
        "required": [
            "fname",
            "lname",
            "userName",
            "dob",
            "gender",
            "contact",
            "address",
            "timezone"
        ],
        "properties": {
            "fname": {
                "type": "string",
                "title": "First Name"
            },
            "lname": {
                "type": "string",
                "title": "Last Name"
            },
            "userName": {
                "type": "string",
                "title": "User Name"
            },
            "dob": {
                "type": "string",
                "title": "Date of Birth",
                "format": "date"
            },
            "gender": {
                "type": "string",
                "title": "Gender",
                "enum": [
                    "Female",
                    "Male",
                    "Other"
                ]
            },
            "contact": {
                "type": "string",
                "title": "Contact"
            },
            "address": {
                "type": "string",
                "title": "Address"
            },
            "timezone": {
                "type": "string",
                "title": "Timezone"
            }
        }
    },
    "4": {
        "title": "Sign Up",
        "type": "object",
        "required": [
            "changemaker",
            "education",
            "language",
            "aboutMe"
        ],
        "properties": {
            "changemaker": {
                "title": "",
                "description": "Type of Changemaker",
                "type": "object",
                "properties": {
                    "specialist": {
                        "type": "string"
                    }
                }
            },
            "education": {
                "type": "array",
                "title": "Educational qualifications",
                "items": {
                    "type": "object",
                    "properties": {
                        "instituteName": {
                            "title": "Institute Name",
                            "type": "string"
                        },
                        "specialization": {
                            "title": "Specialization",
                            "type": "string"
                        },
                        "yearOfPassing": {
                            "title": "Year of Passing",
                            "type": "string"
                        },
                        "typeOfDegree": {
                            "type": "string",
                            "title": "Type of Degree",
                            "enum": [
                                "Bachelors",
                                "Master",
                                "Diploma",
                                "Certification"
                            ]
                        }
                    },
                    "required": [
                        "instituteName",
                        "specialization",
                        "yearOfPassing",
                        "typeOfDegree"
                    ]
                }
            },
            "language": {
                "type": "string",
                "title": "Language Spoken"
            },
            "aboutMe": {
                "type": "string",
                "title": "About me"
            }
        }
    },
    "5": {
        "title": "Sign Up",
        "type": "object",
        "required": [
            "multipleChoicesList"
        ],
        "properties": {
            "multipleChoicesList": {
                "type": "array",
                "title": "Select the Modules (for Changemaker dashboard)",
                "items": {
                    "type": "string",
                    "enum": [
                        "Fitness",
                        "Nutrition",
                        "Mental Health",
                        "Activities",
                        "Teach"
                    ]
                },
                "uniqueItems": true
            }
        }
    }
}